lab2/add2.v
module add2(a, b, c, d, sum, ov);

	input [3:0] a, b, c, d;
	output [4:0] sum;
	output ov;
	
	assign sum = a + b + c + d;
	assign ov = 1'b0;
		
endmodule

lab2/testbench_add2.v
`timescale 1ns / 1ps
module testbench_add2;

reg [3:0] a, b, c, d;
wire [4:0] sum;
wire ov;
reg clk;
reg	rst;
reg [4:0] correct_sum;
reg [15:0] test_num;
reg correct_ov;


always #5 clk = ~clk;

always #5 rst = ~rst;

add2 DUT(a, b, c, d, sum, ov);

initial
begin
	clk <= 0;
	rst <= 0;
	a <= 0; 
	b <= 0;
	c <= 0;
	d <= 0;
	test_num <= 0;
	$dumpfile("add2.vcd");
	$dumpvars;
end

always@(posedge clk or negedge rst)
begin
	if(rst)begin
		if(a <= 15) begin 
			a <= a + 5; //間隔相加為5
			test_num <= test_num + 1;
		end 
		if(a == 15) begin
			b <= b + 5;
		end
		if(a == 15 && b == 15) begin
			c <= c + 5;
		end
		if(a == 15 && b == 15 && c == 15) begin
			d <= d + 5;
		end
	end
	else begin
		{correct_ov, correct_sum} = a + b + c + d;
		if({ov, sum} == {correct_ov, correct_sum}) begin
			$display ("Test %d ", test_num);
			$display ("CORRECT! No overflow.");
			$display ("%d + %d + %d + %d = ?", a, b, c, d);
			$display ("your answer: ov = %d, sum = %d", ov, sum);
			$display ("correct answer: ov = %d, sum = %d", ov, sum);
			$display ("\n");
		end
		else begin
			$display ("Test %d ", test_num);
			$display ("///////////////////////");
			$display ("//////// Fail! ////////");
			$display ("/// Occur Overflow! ///");
			$display ("///////////////////////");
			$display ("%d + %d + %d + %d = ?", a, b, c, d);
			$display ("your answer: ov = %d, sum = %d", ov, sum);
			$display ("correct answer: ov = %d, sum = %d", correct_ov, correct_sum);
			$display ("\n");
		end
	end
end
//initial #13 $finish;
initial #131075 $finish;
//initial #655355 $finish;
endmodule

lab2/add2.vcd
$date
	Mon Mar 22 18:43:09 2021
$end
$version
	Icarus Verilog
$end
$timescale
	1ps
$end
$scope module testbench_add2 $end
$var wire 1 ! ov $end
$var wire 5 " sum [4:0] $end
$var reg 4 # a [3:0] $end
$var reg 4 $ b [3:0] $end
$var reg 4 % c [3:0] $end
$var reg 1 & clk $end
$var reg 1 ' correct_ov $end
$var reg 5 ( correct_sum [4:0] $end
$var reg 4 ) d [3:0] $end
$var reg 1 * rst $end
$var reg 16 + test_num [15:0] $end
$scope module DUT $end
$var wire 4 , a [3:0] $end
$var wire 4 - b [3:0] $end
$var wire 4 . c [3:0] $end
$var wire 4 / d [3:0] $end
$var wire 1 ! ov $end
$var wire 5 0 sum [4:0] $end
$upscope $end
$upscope $end
$enddefinitions $end
#0
$dumpvars
b0 0
b0 /
b0 .
b0 -
b0 ,
b0 +
0*
b0 )
b0 (
0'
0&
b0 %
b0 $
b0 #
b0 "
0!
$end
#5000
b1 +
b101 "
b101 0
b101 #
b101 ,
1*
1&
#10000
b101 (
0*
0&
#15000
b10 +
b1010 "
b1010 0
b1010 #
b1010 ,
1*
1&
#20000
b1010 (
0*
0&
#25000
b11 +
b1111 "
b1111 0
b1111 #
b1111 ,
1*
1&
#30000
b1111 (
0*
0&
#35000
b101 $
b101 -
b100 +
b1001 "
b1001 0
b100 #
b100 ,
1*
1&
#40000
b1001 (
0*
0&
#45000
b101 +
b1110 "
b1110 0
b1001 #
b1001 ,
1*
1&
#50000
b1110 (
0*
0&
#55000
b110 +
b10011 "
b10011 0
b1110 #
b1110 ,
1*
1&
#60000
b10011 (
0*
0&
#65000
b111 +
b1000 "
b1000 0
b11 #
b11 ,
1*
1&
#70000
b1000 (
0*
0&
#75000
b1000 +
b1101 "
b1101 0
b1000 #
b1000 ,
1*
1&
#80000
b1101 (
0*
0&
#85000
b1001 +
b10010 "
b10010 0
b1101 #
b1101 ,
1*
1&
#90000
b10010 (
0*
0&
#95000
b1010 +
b111 "
b111 0
b10 #
b10 ,
1*
1&
#100000
b111 (
0*
0&
#105000
b1011 +
b1100 "
b1100 0
b111 #
b111 ,
1*
1&
#110000
b1100 (
0*
0&
#115000
b1100 +
b10001 "
b10001 0
b1100 #
b1100 ,
1*
1&
#120000
b10001 (
0*
0&
#125000
b1101 +
b110 "
b110 0
b1 #
b1 ,
1*
1&
#130000
b110 (
0*
0&
#135000
b1110 +
b1011 "
b1011 0
b110 #
b110 ,
1*
1&
#140000
b1011 (
0*
0&
#145000
b1111 +
b10000 "
b10000 0
b1011 #
b1011 ,
1*
1&
#150000
b10000 (
0*
0&
#155000
b10000 +
b101 "
b101 0
b0 #
b0 ,
1*
1&
#160000
b101 (
0*
0&
#165000
b10001 +
b1010 "
b1010 0
b101 #
b101 ,
1*
1&
#170000
b1010 (
0*
0&
#175000
b10010 +
b1111 "
b1111 0
b1010 #
b1010 ,
1*
1&
#180000
b1111 (
0*
0&
#185000
b10011 +
b10100 "
b10100 0
b1111 #
b1111 ,
1*
1&
#190000
b10100 (
0*
0&
#195000
b1010 $
b1010 -
b10100 +
b1110 "
b1110 0
b100 #
b100 ,
1*
1&
#200000
b1110 (
0*
0&
#205000
b10101 +
b10011 "
b10011 0
b1001 #
b1001 ,
1*
1&
#210000
b10011 (
0*
0&
#215000
b10110 +
b11000 "
b11000 0
b1110 #
b1110 ,
1*
1&
#220000
b11000 (
0*
0&
#225000
b10111 +
b1101 "
b1101 0
b11 #
b11 ,
1*
1&
#230000
b1101 (
0*
0&
#235000
b11000 +
b10010 "
b10010 0
b1000 #
b1000 ,
1*
1&
#240000
b10010 (
0*
0&
#245000
b11001 +
b10111 "
b10111 0
b1101 #
b1101 ,
1*
1&
#250000
b10111 (
0*
0&
#255000
b11010 +
b1100 "
b1100 0
b10 #
b10 ,
1*
1&
#260000
b1100 (
0*
0&
#265000
b11011 +
b10001 "
b10001 0
b111 #
b111 ,
1*
1&
#270000
b10001 (
0*
0&
#275000
b11100 +
b10110 "
b10110 0
b1100 #
b1100 ,
1*
1&
#280000
b10110 (
0*
0&
#285000
b11101 +
b1011 "
b1011 0
b1 #
b1 ,
1*
1&
#290000
b1011 (
0*
0&
#295000
b11110 +
b10000 "
b10000 0
b110 #
b110 ,
1*
1&
#300000
b10000 (
0*
0&
#305000
b11111 +
b10101 "
b10101 0
b1011 #
b1011 ,
1*
1&
#310000
b10101 (
0*
0&
#315000
b100000 +
b1010 "
b1010 0
b0 #
b0 ,
1*
1&
#320000
b1010 (
0*
0&
#325000
b100001 +
b1111 "
b1111 0
b101 #
b101 ,
1*
1&
#330000
b1111 (
0*
0&
#335000
b100010 +
b10100 "
b10100 0
b1010 #
b1010 ,
1*
1&
#340000
b10100 (
0*
0&
#345000
b100011 +
b11001 "
b11001 0
b1111 #
b1111 ,
1*
1&
#350000
b11001 (
0*
0&
#355000
b1111 $
b1111 -
b100100 +
b10011 "
b10011 0
b100 #
b100 ,
1*
1&
#360000
b10011 (
0*
0&
#365000
b100101 +
b11000 "
b11000 0
b1001 #
b1001 ,
1*
1&
#370000
b11000 (
0*
0&
#375000
b100110 +
b11101 "
b11101 0
b1110 #
b1110 ,
1*
1&
#380000
b11101 (
0*
0&
#385000
b100111 +
b10010 "
b10010 0
b11 #
b11 ,
1*
1&
#390000
b10010 (
0*
0&
#395000
b101000 +
b10111 "
b10111 0
b1000 #
b1000 ,
1*
1&
#400000
b10111 (
0*
0&
#405000
b101001 +
b11100 "
b11100 0
b1101 #
b1101 ,
1*
1&
#410000
b11100 (
0*
0&
#415000
b101010 +
b10001 "
b10001 0
b10 #
b10 ,
1*
1&
#420000
b10001 (
0*
0&
#425000
b101011 +
b10110 "
b10110 0
b111 #
b111 ,
1*
1&
#430000
b10110 (
0*
0&
#435000
b101100 +
b11011 "
b11011 0
b1100 #
b1100 ,
1*
1&
#440000
b11011 (
0*
0&
#445000
b101101 +
b10000 "
b10000 0
b1 #
b1 ,
1*
1&
#450000
b10000 (
0*
0&
#455000
b101110 +
b10101 "
b10101 0
b110 #
b110 ,
1*
1&
#460000
b10101 (
0*
0&
#465000
b101111 +
b11010 "
b11010 0
b1011 #
b1011 ,
1*
1&
#470000
b11010 (
0*
0&
#475000
b110000 +
b1111 "
b1111 0
b0 #
b0 ,
1*
1&
#480000
b1111 (
0*
0&
#485000
b110001 +
b10100 "
b10100 0
b101 #
b101 ,
1*
1&
#490000
b10100 (
0*
0&
#495000
b110010 +
b11001 "
b11001 0
b1010 #
b1010 ,
1*
1&
#500000
b11001 (
0*
0&
#505000
b110011 +
b11110 "
b11110 0
b1111 #
b1111 ,
1*
1&
#510000
b11110 (
0*
0&
#515000
b101 %
b101 .
b100 $
b100 -
b110100 +
b1101 "
b1101 0
b100 #
b100 ,
1*
1&
#520000
b1101 (
0*
0&
#525000
b110101 +
b10010 "
b10010 0
b1001 #
b1001 ,
1*
1&
#530000
b10010 (
0*
0&
#535000
b110110 +
b10111 "
b10111 0
b1110 #
b1110 ,
1*
1&
#540000
b10111 (
0*
0&
#545000
b110111 +
b1100 "
b1100 0
b11 #
b11 ,
1*
1&
#550000
b1100 (
0*
0&
#555000
b111000 +
b10001 "
b10001 0
b1000 #
b1000 ,
1*
1&
#560000
b10001 (
0*
0&
#565000
b111001 +
b10110 "
b10110 0
b1101 #
b1101 ,
1*
1&
#570000
b10110 (
0*
0&
#575000
b111010 +
b1011 "
b1011 0
b10 #
b10 ,
1*
1&
#580000
b1011 (
0*
0&
#585000
b111011 +
b10000 "
b10000 0
b111 #
b111 ,
1*
1&
#590000
b10000 (
0*
0&
#595000
b111100 +
b10101 "
b10101 0
b1100 #
b1100 ,
1*
1&
#600000
b10101 (
0*
0&
#605000
b111101 +
b1010 "
b1010 0
b1 #
b1 ,
1*
1&
#610000
b1010 (
0*
0&
#615000
b111110 +
b1111 "
b1111 0
b110 #
b110 ,
1*
1&
#620000
b1111 (
0*
0&
#625000
b111111 +
b10100 "
b10100 0
b1011 #
b1011 ,
1*
1&
#630000
b10100 (
0*
0&
#635000
b1000000 +
b1001 "
b1001 0
b0 #
b0 ,
1*
1&
#640000
b1001 (
0*
0&
#645000
b1000001 +
b1110 "
b1110 0
b101 #
b101 ,
1*
1&
#650000
b1110 (
0*
0&
#655000
b1000010 +
b10011 "
b10011 0
b1010 #
b1010 ,
1*
1&
#660000
b10011 (
0*
0&
#665000
b1000011 +
b11000 "
b11000 0
b1111 #
b1111 ,
1*
1&
#670000
b11000 (
0*
0&
#675000
b1001 $
b1001 -
b1000100 +
b10010 "
b10010 0
b100 #
b100 ,
1*
1&
#680000
b10010 (
0*
0&
#685000
b1000101 +
b10111 "
b10111 0
b1001 #
b1001 ,
1*
1&
#690000
b10111 (
0*
0&
#695000
b1000110 +
b11100 "
b11100 0
b1110 #
b1110 ,
1*
1&
#700000
b11100 (
0*
0&
#705000
b1000111 +
b10001 "
b10001 0
b11 #
b11 ,
1*
1&
#710000
b10001 (
0*
0&
#715000
b1001000 +
b10110 "
b10110 0
b1000 #
b1000 ,
1*
1&
#720000
b10110 (
0*
0&
#725000
b1001001 +
b11011 "
b11011 0
b1101 #
b1101 ,
1*
1&
#730000
b11011 (
0*
0&
#735000
b1001010 +
b10000 "
b10000 0
b10 #
b10 ,
1*
1&
#740000
b10000 (
0*
0&
#745000
b1001011 +
b10101 "
b10101 0
b111 #
b111 ,
1*
1&
#750000
b10101 (
0*
0&
#755000
b1001100 +
b11010 "
b11010 0
b1100 #
b1100 ,
1*
1&
#760000
b11010 (
0*
0&
#765000
b1001101 +
b1111 "
b1111 0
b1 #
b1 ,
1*
1&
#770000
b1111 (
0*
0&
#775000
b1001110 +
b10100 "
b10100 0
b110 #
b110 ,
1*
1&
#780000
b10100 (
0*
0&
#785000
b1001111 +
b11001 "
b11001 0
b1011 #
b1011 ,
1*
1&
#790000
b11001 (
0*
0&
#795000
b1010000 +
b1110 "
b1110 0
b0 #
b0 ,
1*
1&
#800000
b1110 (
0*
0&
#805000
b1010001 +
b10011 "
b10011 0
b101 #
b101 ,
1*
1&
#810000
b10011 (
0*
0&
#815000
b1010010 +
b11000 "
b11000 0
b1010 #
b1010 ,
1*
1&
#820000
b11000 (
0*
0&
#825000
b1010011 +
b11101 "
b11101 0
b1111 #
b1111 ,
1*
1&
#830000
b11101 (
0*
0&
#835000
b1110 $
b1110 -
b1010100 +
b10111 "
b10111 0
b100 #
b100 ,
1*
1&
#840000
b10111 (
0*
0&
#845000
b1010101 +
b11100 "
b11100 0
b1001 #
b1001 ,
1*
1&
#850000
b11100 (
0*
0&
#855000
b1010110 +
b1 "
b1 0
b1110 #
b1110 ,
1*
1&
#860000
1'
b1 (
0*
0&
#865000
b1010111 +
b10110 "
b10110 0
b11 #
b11 ,
1*
1&
#870000
0'
b10110 (
0*
0&
#875000
b1011000 +
b11011 "
b11011 0
b1000 #
b1000 ,
1*
1&
#880000
b11011 (
0*
0&
#885000
b1011001 +
b0 "
b0 0
b1101 #
b1101 ,
1*
1&
#890000
1'
b0 (
0*
0&
#895000
b1011010 +
b10101 "
b10101 0
b10 #
b10 ,
1*
1&
#900000
0'
b10101 (
0*
0&
#905000
b1011011 +
b11010 "
b11010 0
b111 #
b111 ,
1*
1&
#910000
b11010 (
0*
0&
#915000
b1011100 +
b11111 "
b11111 0
b1100 #
b1100 ,
1*
1&
#920000
b11111 (
0*
0&
#925000
b1011101 +
b10100 "
b10100 0
b1 #
b1 ,
1*
1&
#930000
b10100 (
0*
0&
#935000
b1011110 +
b11001 "
b11001 0
b110 #
b110 ,
1*
1&
#940000
b11001 (
0*
0&
#945000
b1011111 +
b11110 "
b11110 0
b1011 #
b1011 ,
1*
1&
#950000
b11110 (
0*
0&
#955000
b1100000 +
b10011 "
b10011 0
b0 #
b0 ,
1*
1&
#960000
b10011 (
0*
0&
#965000
b1100001 +
b11000 "
b11000 0
b101 #
b101 ,
1*
1&
#970000
b11000 (
0*
0&
#975000
b1100010 +
b11101 "
b11101 0
b1010 #
b1010 ,
1*
1&
#980000
b11101 (
0*
0&
#985000
b1100011 +
b10 "
b10 0
b1111 #
b1111 ,
1*
1&
#990000
1'
b10 (
0*
0&
#995000
b11 $
b11 -
b1100100 +
b1100 "
b1100 0
b100 #
b100 ,
1*
1&
#1000000
0'
b1100 (
0*
0&
#1005000
b1100101 +
b10001 "
b10001 0
b1001 #
b1001 ,
1*
1&
#1010000
b10001 (
0*
0&
#1015000
b1100110 +
b10110 "
b10110 0
b1110 #
b1110 ,
1*
1&
#1020000
b10110 (
0*
0&
#1025000
b1100111 +
b1011 "
b1011 0
b11 #
b11 ,
1*
1&
#1030000
b1011 (
0*
0&
#1035000
b1101000 +
b10000 "
b10000 0
b1000 #
b1000 ,
1*
1&
#1040000
b10000 (
0*
0&
#1045000
b1101001 +
b10101 "
b10101 0
b1101 #
b1101 ,
1*
1&
#1050000
b10101 (
0*
0&
#1055000
b1101010 +
b1010 "
b1010 0
b10 #
b10 ,
1*
1&
#1060000
b1010 (
0*
0&
#1065000
b1101011 +
b1111 "
b1111 0
b111 #
b111 ,
1*
1&
#1070000
b1111 (
0*
0&
#1075000
b1101100 +
b10100 "
b10100 0
b1100 #
b1100 ,
1*
1&
#1080000
b10100 (
0*
0&
#1085000
b1101101 +
b1001 "
b1001 0
b1 #
b1 ,
1*
1&
#1090000
b1001 (
0*
0&
#1095000
b1101110 +
b1110 "
b1110 0
b110 #
b110 ,
1*
1&
#1100000
b1110 (
0*
0&
#1105000
b1101111 +
b10011 "
b10011 0
b1011 #
b1011 ,
1*
1&
#1110000
b10011 (
0*
0&
#1115000
b1110000 +
b1000 "
b1000 0
b0 #
b0 ,
1*
1&
#1120000
b1000 (
0*
0&
#1125000
b1110001 +
b1101 "
b1101 0
b101 #
b101 ,
1*
1&
#1130000
b1101 (
0*
0&
#1135000
b1110010 +
b10010 "
b10010 0
b1010 #
b1010 ,
1*
1&
#1140000
b10010 (
0*
0&
#1145000
b1110011 +
b10111 "
b10111 0
b1111 #
b1111 ,
1*
1&
#1150000
b10111 (
0*
0&
#1155000
b1000 $
b1000 -
b1110100 +
b10001 "
b10001 0
b100 #
b100 ,
1*
1&
#1160000
b10001 (
0*
0&
#1165000
b1110101 +
b10110 "
b10110 0
b1001 #
b1001 ,
1*
1&
#1170000
b10110 (
0*
0&
#1175000
b1110110 +
b11011 "
b11011 0
b1110 #
b1110 ,
1*
1&
#1180000
b11011 (
0*
0&
#1185000
b1110111 +
b10000 "
b10000 0
b11 #
b11 ,
1*
1&
#1190000
b10000 (
0*
0&
#1195000
b1111000 +
b10101 "
b10101 0
b1000 #
b1000 ,
1*
1&
#1200000
b10101 (
0*
0&
#1205000
b1111001 +
b11010 "
b11010 0
b1101 #
b1101 ,
1*
1&
#1210000
b11010 (
0*
0&
#1215000
b1111010 +
b1111 "
b1111 0
b10 #
b10 ,
1*
1&
#1220000
b1111 (
0*
0&
#1225000
b1111011 +
b10100 "
b10100 0
b111 #
b111 ,
1*
1&
#1230000
b10100 (
0*
0&
#1235000
b1111100 +
b11001 "
b11001 0
b1100 #
b1100 ,
1*
1&
#1240000
b11001 (
0*
0&
#1245000
b1111101 +
b1110 "
b1110 0
b1 #
b1 ,
1*
1&
#1250000
b1110 (
0*
0&
#1255000
b1111110 +
b10011 "
b10011 0
b110 #
b110 ,
1*
1&
#1260000
b10011 (
0*
0&
#1265000
b1111111 +
b11000 "
b11000 0
b1011 #
b1011 ,
1*
1&
#1270000
b11000 (
0*
0&
#1275000
b10000000 +
b1101 "
b1101 0
b0 #
b0 ,
1*
1&
#1280000
b1101 (
0*
0&
#1285000
b10000001 +
b10010 "
b10010 0
b101 #
b101 ,
1*
1&
#1290000
b10010 (
0*
0&
#1295000
b10000010 +
b10111 "
b10111 0
b1010 #
b1010 ,
1*
1&
#1300000
b10111 (
0*
0&
#1305000
b10000011 +
b11100 "
b11100 0
b1111 #
b1111 ,
1*
1&
#1310000
b11100 (
0*
0&
#1315000
b1101 $
b1101 -
b10000100 +
b10110 "
b10110 0
b100 #
b100 ,
1*
1&
#1320000
b10110 (
0*
0&
#1325000
b10000101 +
b11011 "
b11011 0
b1001 #
b1001 ,
1*
1&
#1330000
b11011 (
0*
0&
#1335000
b10000110 +
b0 "
b0 0
b1110 #
b1110 ,
1*
1&
#1340000
1'
b0 (
0*
0&
#1345000
b10000111 +
b10101 "
b10101 0
b11 #
b11 ,
1*
1&
#1350000
0'
b10101 (
0*
0&
#1355000
b10001000 +
b11010 "
b11010 0
b1000 #
b1000 ,
1*
1&
#1360000
b11010 (
0*
0&
#1365000
b10001001 +
b11111 "
b11111 0
b1101 #
b1101 ,
1*
1&
#1370000
b11111 (
0*
0&
#1375000
b10001010 +
b10100 "
b10100 0
b10 #
b10 ,
1*
1&
#1380000
b10100 (
0*
0&
#1385000
b10001011 +
b11001 "
b11001 0
b111 #
b111 ,
1*
1&
#1390000
b11001 (
0*
0&
#1395000
b10001100 +
b11110 "
b11110 0
b1100 #
b1100 ,
1*
1&
#1400000
b11110 (
0*
0&
#1405000
b10001101 +
b10011 "
b10011 0
b1 #
b1 ,
1*
1&
#1410000
b10011 (
0*
0&
#1415000
b10001110 +
b11000 "
b11000 0
b110 #
b110 ,
1*
1&
#1420000
b11000 (
0*
0&
#1425000
b10001111 +
b11101 "
b11101 0
b1011 #
b1011 ,
1*
1&
#1430000
b11101 (
0*
0&
#1435000
b10010000 +
b10010 "
b10010 0
b0 #
b0 ,
1*
1&
#1440000
b10010 (
0*
0&
#1445000
b10010001 +
b10111 "
b10111 0
b101 #
b101 ,
1*
1&
#1450000
b10111 (
0*
0&
#1455000
b10010010 +
b11100 "
b11100 0
b1010 #
b1010 ,
1*
1&
#1460000
b11100 (
0*
0&
#1465000
b10010011 +
b1 "
b1 0
b1111 #
b1111 ,
1*
1&
#1470000
1'
b1 (
0*
0&
#1475000
b10 $
b10 -
b10010100 +
b1011 "
b1011 0
b100 #
b100 ,
1*
1&
#1480000
0'
b1011 (
0*
0&
#1485000
b10010101 +
b10000 "
b10000 0
b1001 #
b1001 ,
1*
1&
#1490000
b10000 (
0*
0&
#1495000
b10010110 +
b10101 "
b10101 0
b1110 #
b1110 ,
1*
1&
#1500000
b10101 (
0*
0&
#1505000
b10010111 +
b1010 "
b1010 0
b11 #
b11 ,
1*
1&
#1510000
b1010 (
0*
0&
#1515000
b10011000 +
b1111 "
b1111 0
b1000 #
b1000 ,
1*
1&
#1520000
b1111 (
0*
0&
#1525000
b10011001 +
b10100 "
b10100 0
b1101 #
b1101 ,
1*
1&
#1530000
b10100 (
0*
0&
#1535000
b10011010 +
b1001 "
b1001 0
b10 #
b10 ,
1*
1&
#1540000
b1001 (
0*
0&
#1545000
b10011011 +
b1110 "
b1110 0
b111 #
b111 ,
1*
1&
#1550000
b1110 (
0*
0&
#1555000
b10011100 +
b10011 "
b10011 0
b1100 #
b1100 ,
1*
1&
#1560000
b10011 (
0*
0&
#1565000
b10011101 +
b1000 "
b1000 0
b1 #
b1 ,
1*
1&
#1570000
b1000 (
0*
0&
#1575000
b10011110 +
b1101 "
b1101 0
b110 #
b110 ,
1*
1&
#1580000
b1101 (
0*
0&
#1585000
b10011111 +
b10010 "
b10010 0
b1011 #
b1011 ,
1*
1&
#1590000
b10010 (
0*
0&
#1595000
b10100000 +
b111 "
b111 0
b0 #
b0 ,
1*
1&
#1600000
b111 (
0*
0&
#1605000
b10100001 +
b1100 "
b1100 0
b101 #
b101 ,
1*
1&
#1610000
b1100 (
0*
0&
#1615000
b10100010 +
b10001 "
b10001 0
b1010 #
b1010 ,
1*
1&
#1620000
b10001 (
0*
0&
#1625000
b10100011 +
b10110 "
b10110 0
b1111 #
b1111 ,
1*
1&
#1630000
b10110 (
0*
0&
#1635000
b111 $
b111 -
b10100100 +
b10000 "
b10000 0
b100 #
b100 ,
1*
1&
#1640000
b10000 (
0*
0&
#1645000
b10100101 +
b10101 "
b10101 0
b1001 #
b1001 ,
1*
1&
#1650000
b10101 (
0*
0&
#1655000
b10100110 +
b11010 "
b11010 0
b1110 #
b1110 ,
1*
1&
#1660000
b11010 (
0*
0&
#1665000
b10100111 +
b1111 "
b1111 0
b11 #
b11 ,
1*
1&
#1670000
b1111 (
0*
0&
#1675000
b10101000 +
b10100 "
b10100 0
b1000 #
b1000 ,
1*
1&
#1680000
b10100 (
0*
0&
#1685000
b10101001 +
b11001 "
b11001 0
b1101 #
b1101 ,
1*
1&
#1690000
b11001 (
0*
0&
#1695000
b10101010 +
b1110 "
b1110 0
b10 #
b10 ,
1*
1&
#1700000
b1110 (
0*
0&
#1705000
b10101011 +
b10011 "
b10011 0
b111 #
b111 ,
1*
1&
#1710000
b10011 (
0*
0&
#1715000
b10101100 +
b11000 "
b11000 0
b1100 #
b1100 ,
1*
1&
#1720000
b11000 (
0*
0&
#1725000
b10101101 +
b1101 "
b1101 0
b1 #
b1 ,
1*
1&
#1730000
b1101 (
0*
0&
#1735000
b10101110 +
b10010 "
b10010 0
b110 #
b110 ,
1*
1&
#1740000
b10010 (
0*
0&
#1745000
b10101111 +
b10111 "
b10111 0
b1011 #
b1011 ,
1*
1&
#1750000
b10111 (
0*
0&
#1755000
b10110000 +
b1100 "
b1100 0
b0 #
b0 ,
1*
1&
#1760000
b1100 (
0*
0&
#1765000
b10110001 +
b10001 "
b10001 0
b101 #
b101 ,
1*
1&
#1770000
b10001 (
0*
0&
#1775000
b10110010 +
b10110 "
b10110 0
b1010 #
b1010 ,
1*
1&
#1780000
b10110 (
0*
0&
#1785000
b10110011 +
b11011 "
b11011 0
b1111 #
b1111 ,
1*
1&
#1790000
b11011 (
0*
0&
#1795000
b1100 $
b1100 -
b10110100 +
b10101 "
b10101 0
b100 #
b100 ,
1*
1&
#1800000
b10101 (
0*
0&
#1805000
b10110101 +
b11010 "
b11010 0
b1001 #
b1001 ,
1*
1&
#1810000
b11010 (
0*
0&
#1815000
b10110110 +
b11111 "
b11111 0
b1110 #
b1110 ,
1*
1&
#1820000
b11111 (
0*
0&
#1825000
b10110111 +
b10100 "
b10100 0
b11 #
b11 ,
1*
1&
#1830000
b10100 (
0*
0&
#1835000
b10111000 +
b11001 "
b11001 0
b1000 #
b1000 ,
1*
1&
#1840000
b11001 (
0*
0&
#1845000
b10111001 +
b11110 "
b11110 0
b1101 #
b1101 ,
1*
1&
#1850000
b11110 (
0*
0&
#1855000
b10111010 +
b10011 "
b10011 0
b10 #
b10 ,
1*
1&
#1860000
b10011 (
0*
0&
#1865000
b10111011 +
b11000 "
b11000 0
b111 #
b111 ,
1*
1&
#1870000
b11000 (
0*
0&
#1875000
b10111100 +
b11101 "
b11101 0
b1100 #
b1100 ,
1*
1&
#1880000
b11101 (
0*
0&
#1885000
b10111101 +
b10010 "
b10010 0
b1 #
b1 ,
1*
1&
#1890000
b10010 (
0*
0&
#1895000
b10111110 +
b10111 "
b10111 0
b110 #
b110 ,
1*
1&
#1900000
b10111 (
0*
0&
#1905000
b10111111 +
b11100 "
b11100 0
b1011 #
b1011 ,
1*
1&
#1910000
b11100 (
0*
0&
#1915000
b11000000 +
b10001 "
b10001 0
b0 #
b0 ,
1*
1&
#1920000
b10001 (
0*
0&
#1925000
b11000001 +
b10110 "
b10110 0
b101 #
b101 ,
1*
1&
#1930000
b10110 (
0*
0&
#1935000
b11000010 +
b11011 "
b11011 0
b1010 #
b1010 ,
1*
1&
#1940000
b11011 (
0*
0&
#1945000
b11000011 +
b0 "
b0 0
b1111 #
b1111 ,
1*
1&
#1950000
1'
b0 (
0*
0&
#1955000
b1 $
b1 -
b11000100 +
b1010 "
b1010 0
b100 #
b100 ,
1*
1&
#1960000
0'
b1010 (
0*
0&
#1965000
b11000101 +
b1111 "
b1111 0
b1001 #
b1001 ,
1*
1&
#1970000
b1111 (
0*
0&
#1975000
b11000110 +
b10100 "
b10100 0
b1110 #
b1110 ,
1*
1&
#1980000
b10100 (
0*
0&
#1985000
b11000111 +
b1001 "
b1001 0
b11 #
b11 ,
1*
1&
#1990000
b1001 (
0*
0&
#1995000
b11001000 +
b1110 "
b1110 0
b1000 #
b1000 ,
1*
1&
#2000000
b1110 (
0*
0&
#2005000
b11001001 +
b10011 "
b10011 0
b1101 #
b1101 ,
1*
1&
#2010000
b10011 (
0*
0&
#2015000
b11001010 +
b1000 "
b1000 0
b10 #
b10 ,
1*
1&
#2020000
b1000 (
0*
0&
#2025000
b11001011 +
b1101 "
b1101 0
b111 #
b111 ,
1*
1&
#2030000
b1101 (
0*
0&
#2035000
b11001100 +
b10010 "
b10010 0
b1100 #
b1100 ,
1*
1&
#2040000
b10010 (
0*
0&
#2045000
b11001101 +
b111 "
b111 0
b1 #
b1 ,
1*
1&
#2050000
b111 (
0*
0&
#2055000
b11001110 +
b1100 "
b1100 0
b110 #
b110 ,
1*
1&
#2060000
b1100 (
0*
0&
#2065000
b11001111 +
b10001 "
b10001 0
b1011 #
b1011 ,
1*
1&
#2070000
b10001 (
0*
0&
#2075000
b11010000 +
b110 "
b110 0
b0 #
b0 ,
1*
1&
#2080000
b110 (
0*
0&
#2085000
b11010001 +
b1011 "
b1011 0
b101 #
b101 ,
1*
1&
#2090000
b1011 (
0*
0&
#2095000
b11010010 +
b10000 "
b10000 0
b1010 #
b1010 ,
1*
1&
#2100000
b10000 (
0*
0&
#2105000
b11010011 +
b10101 "
b10101 0
b1111 #
b1111 ,
1*
1&
#2110000
b10101 (
0*
0&
#2115000
b110 $
b110 -
b11010100 +
b1111 "
b1111 0
b100 #
b100 ,
1*
1&
#2120000
b1111 (
0*
0&
#2125000
b11010101 +
b10100 "
b10100 0
b1001 #
b1001 ,
1*
1&
#2130000
b10100 (
0*
0&
#2135000
b11010110 +
b11001 "
b11001 0
b1110 #
b1110 ,
1*
1&
#2140000
b11001 (
0*
0&
#2145000
b11010111 +
b1110 "
b1110 0
b11 #
b11 ,
1*
1&
#2150000
b1110 (
0*
0&
#2155000
b11011000 +
b10011 "
b10011 0
b1000 #
b1000 ,
1*
1&
#2160000
b10011 (
0*
0&
#2165000
b11011001 +
b11000 "
b11000 0
b1101 #
b1101 ,
1*
1&
#2170000
b11000 (
0*
0&
#2175000
b11011010 +
b1101 "
b1101 0
b10 #
b10 ,
1*
1&
#2180000
b1101 (
0*
0&
#2185000
b11011011 +
b10010 "
b10010 0
b111 #
b111 ,
1*
1&
#2190000
b10010 (
0*
0&
#2195000
b11011100 +
b10111 "
b10111 0
b1100 #
b1100 ,
1*
1&
#2200000
b10111 (
0*
0&
#2205000
b11011101 +
b1100 "
b1100 0
b1 #
b1 ,
1*
1&
#2210000
b1100 (
0*
0&
#2215000
b11011110 +
b10001 "
b10001 0
b110 #
b110 ,
1*
1&
#2220000
b10001 (
0*
0&
#2225000
b11011111 +
b10110 "
b10110 0
b1011 #
b1011 ,
1*
1&
#2230000
b10110 (
0*
0&
#2235000
b11100000 +
b1011 "
b1011 0
b0 #
b0 ,
1*
1&
#2240000
b1011 (
0*
0&
#2245000
b11100001 +
b10000 "
b10000 0
b101 #
b101 ,
1*
1&
#2250000
b10000 (
0*
0&
#2255000
b11100010 +
b10101 "
b10101 0
b1010 #
b1010 ,
1*
1&
#2260000
b10101 (
0*
0&
#2265000
b11100011 +
b11010 "
b11010 0
b1111 #
b1111 ,
1*
1&
#2270000
b11010 (
0*
0&
#2275000
b1011 $
b1011 -
b11100100 +
b10100 "
b10100 0
b100 #
b100 ,
1*
1&
#2280000
b10100 (
0*
0&
#2285000
b11100101 +
b11001 "
b11001 0
b1001 #
b1001 ,
1*
1&
#2290000
b11001 (
0*
0&
#2295000
b11100110 +
b11110 "
b11110 0
b1110 #
b1110 ,
1*
1&
#2300000
b11110 (
0*
0&
#2305000
b11100111 +
b10011 "
b10011 0
b11 #
b11 ,
1*
1&
#2310000
b10011 (
0*
0&
